steam_nb_api/__init__.py
steam_nb_api/ledet/AutomaticSweep.py
steam_nb_api/ledet/NeighbourHalfTurnsCalculation.py
steam_nb_api/ledet/NotebookLEDET.py
steam_nb_api/ledet/NotebookLEDET_V2.py
steam_nb_api/ledet/ParameterSweep.py
steam_nb_api/ledet/ParametersLEDET.py
steam_nb_api/ledet/QuenchAnalysis.py
steam_nb_api/ledet/RunParameterSweep.py
steam_nb_api/ledet/Simulation.py
steam_nb_api/ledet/SimulationEvaluation.py
steam_nb_api/ledet/Solenoids.py
steam_nb_api/ledet/__init__.py
steam_nb_api/magnetic_analysis/__init__.py
steam_nb_api/resources/ResourceReader.py
steam_nb_api/resources/__init__.py
steam_nb_api/resources/ledet/__init__.py
steam_nb_api/resources/ledet/variableNamesDescriptions.xlsx
steam_nb_api/resources/ledet/Inputs/__init__.py
steam_nb_api/resources/ledet/Inputs/circuit.120A.yaml
steam_nb_api/resources/ledet/Inputs/circuit.600A.yaml
steam_nb_api/resources/ledet/Inputs/conductor.Type2.yaml
steam_nb_api/resources/ledet/Inputs/conductor.Type3.yaml
steam_nb_api/resources/ledet/Inputs/conductor.W1.yaml
steam_nb_api/resources/ledet/Inputs/magnet.Dummy.yaml
steam_nb_api/resources/ledet/Inputs/magnet.MLEA.yaml
steam_nb_api/resources/ledet/Inputs/magnet.MLEB.yaml
steam_nb_api/resources/ledet/Inputs/magnet.MLEC.yaml
steam_nb_api/resources/ledet/Inputs/magnet.MLEG.yaml
steam_nb_api/resources/ledet/Inputs/magnet.MLEM.yaml
steam_nb_api/resources/ledet/Inputs/magnet.MainSolenoid.yaml
steam_nb_api/resources/ledet/Inputs/magnet.MainSolenoid_New.yaml
steam_nb_api/resources/ledet/Inputs/options.Default.yaml
steam_nb_api/resources/ledet/Inputs/options.cos_theta.yaml
steam_nb_api/resources/ledet/Inputs/options.solenoid.yaml
steam_nb_api/resources/ledet/Inputs/plots.Default.yaml
steam_nb_api/resources/ledet/Inputs/protection.EE500V.yaml
steam_nb_api/resources/ledet/Inputs/protection.NoEE.yaml
steam_nb_api/resources/ledet/Inputs/scenario.Dummy.yaml
steam_nb_api/resources/ledet/Inputs/scenario.MLEA.yaml
steam_nb_api/resources/ledet/Inputs/scenario.MLEB.yaml
steam_nb_api-0.3.29.dist-info/METADATA
steam_nb_api-0.3.29.dist-info/WHEEL
steam_nb_api-0.3.29.dist-info/top_level.txt
steam_nb_api-0.3.29.dist-info/RECORD
