Metadata-Version: 2.1
Name: steam-nb-api
Version: 0.3.29
Summary: A package with an API for STEAM.
Home-page: https://gitlab.cern.ch/steam/steam-notebook-api
Author: TE-MPE
Author-email: steam@cern.ch
License: UNKNOWN
Platform: UNKNOWN
Classifier: Programming Language :: Python :: 3
Classifier: License :: OSI Approved :: MIT License
Classifier: Operating System :: OS Independent
